meshrender/__init__.py
meshrender/camera.py
meshrender/constants.py
meshrender/light.py
meshrender/material.py
meshrender/random_variables.py
meshrender/render.py
meshrender/scene.py
meshrender/scene_object.py
meshrender/shaders.py
meshrender/trackball.py
meshrender/version.py
meshrender/viewer.py
meshrender-0.0.9.dist-info/LICENSE
meshrender-0.0.9.dist-info/METADATA
meshrender-0.0.9.dist-info/WHEEL
meshrender-0.0.9.dist-info/top_level.txt
meshrender-0.0.9.dist-info/RECORD
