Metadata-Version: 2.1
Name: meshrender
Version: 0.0.9
Summary: Python utilities for rendering scenes containing 3D meshes
Home-page: https://github.com/BerkeleyAutomation/meshrender
Author: Matthew Matl
Author-email: mmatl@eecs.berkeley.edu
License: Apache Software License
Keywords: rendering opengl 3d visualization
Platform: UNKNOWN
Classifier: Development Status :: 3 - Alpha
Classifier: License :: OSI Approved :: Apache Software License
Classifier: Operating System :: POSIX :: Linux
Classifier: Operating System :: MacOS :: MacOS X
Classifier: Programming Language :: Python :: 2.7
Classifier: Programming Language :: Python :: 3.5
Classifier: Programming Language :: Python :: 3.6
Provides-Extra: docs
